asm_api/__init__.py
asm_api/asm_api.py
asm_api/api/__init__.py
asm_api/api/client_api.py
asm_api-0.0.20.data/data/README/README.md
asm_api-0.0.20.dist-info/DESCRIPTION.rst
asm_api-0.0.20.dist-info/METADATA
asm_api-0.0.20.dist-info/RECORD
asm_api-0.0.20.dist-info/WHEEL
asm_api-0.0.20.dist-info/metadata.json
asm_api-0.0.20.dist-info/top_level.txt
