Metadata-Version: 2.0
Name: asm-api
Version: 0.0.20
Summary: Command line interface for Alphalogic Service Manager.
Home-page: https://github.com/Alphaopen/asm_api
Author: Alphaopen
Author-email: mo@alphaopen.com
License: MIT
Platform: linux2
Platform: win32
Classifier: Programming Language :: Python :: 2.7
Classifier: License :: OSI Approved :: MIT License
Classifier: Operating System :: OS Independent
Requires-Dist: requests (>=2.19.1)
